{
  "status": "completed",
  "folderName": "Office\\TP-Link\\samsung_galaxy_S10/vimeo_android",
  "createdAt": "2026-06-18T16:03:16",
  "durationSeconds": 1200.0,
  "sampleCount": 238043,
  "smooth": true,
  "showRaw": true,
  "smoothWindow": 11,
  "experimentContext": {
    "runId": "office-samsung-galaxy-s10-vimeo-android-rep-1-20260618T061549735438Z",
    "experimentId": "Office",
    "environmentId": "office",
    "deviceId": "samsung_galaxy_S10",
    "hardwareId": "arduino_vcap_com3",
    "routerId": "TP-Link",
    "appId": "vimeo_android",
    "appLabel": "vimeo_android",
    "durationSec": 1200,
    "appWarmupSec": 60,
    "repetitionId": 1,
    "outputDir": "data\\raw\\Office\\TP-Link\\samsung_galaxy_S10\\vimeo_android"
  },
  "rawHeader": [
    "Time(ms)",
    "ADC",
    "Voltage(V)"
  ],
  "files": {
    "rawCsv": "Data\\Office\\TP-Link\\samsung_galaxy_S10\\vimeo_android\\vimeo_android.csv",
    "plot": "Data\\Office\\TP-Link\\samsung_galaxy_S10\\vimeo_android\\vimeo_android.png"
  },
  "error": "",
  "result": {
    "reason": "duration reached",
    "completedAt": "2026-06-18T16:03:16",
    "sampleCount": 238043,
    "csvPath": "Data\\Office\\TP-Link\\samsung_galaxy_S10\\vimeo_android\\vimeo_android.csv",
    "pngPath": "Data\\Office\\TP-Link\\samsung_galaxy_S10\\vimeo_android\\vimeo_android.png"
  }
}